aqt/__init__.py
aqt/_macos_helper.py
aqt/about.py
aqt/addcards.py
aqt/addons.py
aqt/ankihub.py
aqt/changenotetype.py
aqt/clayout.py
aqt/colors.py
aqt/customstudy.py
aqt/dbcheck.py
aqt/debug_console.py
aqt/deckbrowser.py
aqt/deckchooser.py
aqt/deckconf.py
aqt/deckdescription.py
aqt/deckoptions.py
aqt/editcurrent.py
aqt/editor.py
aqt/emptycards.py
aqt/errors.py
aqt/exporting.py
aqt/fields.py
aqt/filtered_deck.py
aqt/flags.py
aqt/gui_hooks.py
aqt/importing.py
aqt/legacy.py
aqt/log.py
aqt/main.py
aqt/mediacheck.py
aqt/mediasrv.py
aqt/mediasync.py
aqt/modelchooser.py
aqt/models.py
aqt/mpv.py
aqt/notetypechooser.py
aqt/overview.py
aqt/package.py
aqt/preferences.py
aqt/profiles.py
aqt/progress.py
aqt/props.py
aqt/py.typed
aqt/reviewer.py
aqt/schema_change_tracker.py
aqt/sound.py
aqt/stats.py
aqt/studydeck.py
aqt/stylesheets.py
aqt/switch.py
aqt/sync.py
aqt/tagedit.py
aqt/taglimit.py
aqt/taskman.py
aqt/theme.py
aqt/toolbar.py
aqt/tts.py
aqt/undo.py
aqt/update.py
aqt/url_schemes.py
aqt/utils.py
aqt/webview.py
aqt/widgetgallery.py
aqt/winpaths.py
aqt/browser/__init__.py
aqt/browser/browser.py
aqt/browser/card_info.py
aqt/browser/find_and_replace.py
aqt/browser/find_duplicates.py
aqt/browser/layout.py
aqt/browser/previewer.py
aqt/browser/sidebar/__init__.py
aqt/browser/sidebar/item.py
aqt/browser/sidebar/model.py
aqt/browser/sidebar/searchbar.py
aqt/browser/sidebar/toolbar.py
aqt/browser/sidebar/tree.py
aqt/browser/table/__init__.py
aqt/browser/table/model.py
aqt/browser/table/state.py
aqt/browser/table/table.py
aqt/forms/__init__.py
aqt/forms/about.py
aqt/forms/addcards.py
aqt/forms/addfield.py
aqt/forms/addmodel.py
aqt/forms/addonconf.py
aqt/forms/addons.py
aqt/forms/browser.py
aqt/forms/browserdisp.py
aqt/forms/browseropts.py
aqt/forms/changemap.py
aqt/forms/changemodel.py
aqt/forms/clayout_top.py
aqt/forms/customstudy.py
aqt/forms/dconf.py
aqt/forms/debug.py
aqt/forms/editcurrent.py
aqt/forms/edithtml.py
aqt/forms/emptycards.py
aqt/forms/exporting.py
aqt/forms/fields.py
aqt-25.9.1.dist-info/METADATA
aqt-25.9.1.dist-info/WHEEL
aqt-25.9.1.dist-info/entry_points.txt
aqt-25.9.1.dist-info/RECORD
